elbooq/__init__.py
elbooq/elbooq.py
elbooq-1.0.2.dist-info/METADATA
elbooq-1.0.2.dist-info/RECORD
elbooq-1.0.2.dist-info/WHEEL
elbooq-1.0.2.dist-info/top_level.txt
