Metadata-Version: 2.1
Name: elbooq
Version: 1.0.2
Summary: Client to Elbooq Payment Gateway
Home-page: https://www.bitbucket.org/labelag/elbooq
Author: Elbooq
Author-email: wecare@elbooq.net
License: MIT
Platform: UNKNOWN
Classifier: Programming Language :: Python :: 2.7
Classifier: Programming Language :: Python :: 3
Classifier: License :: OSI Approved :: MIT License
Classifier: Operating System :: OS Independent
Requires-Dist: requests
